[
  {
    "function_v0": {
      "doc": "",
      "name": "asset",
      "inputs": [],
      "outputs": [
        "address"
      ]
    }
  },
  {
    "function_v0": {
      "doc": "",
      "name": "balance",
      "inputs": [
        {
          "doc": "",
          "name": "from",
          "type_": "address"
        }
      ],
      "outputs": [
        "i128"
      ]
    }
  },
  {
    "function_v0": {
      "doc": "",
      "name": "deposit",
      "inputs": [
        {
          "doc": "",
          "name": "amount",
          "type_": "i128"
        },
        {
          "doc": "",
          "name": "from",
          "type_": "address"
        }
      ],
      "outputs": [
        "i128"
      ]
    }
  },
  {
    "function_v0": {
      "doc": "v1 mainnet: no-op. AQUA pool_index for AQUA/asset is unverified and\\npools may be thin. Future v1.1: claim + swap + compound like Blend.",
      "name": "harvest",
      "inputs": [
        {
          "doc": "",
          "name": "from",
          "type_": "address"
        }
      ],
      "outputs": [
        "i128"
      ]
    }
  },
  {
    "function_v0": {
      "doc": "",
      "name": "registry",
      "inputs": [],
      "outputs": [
        "address"
      ]
    }
  },
  {
    "function_v0": {
      "doc": "",
      "name": "withdraw",
      "inputs": [
        {
          "doc": "",
          "name": "amount",
          "type_": "i128"
        },
        {
          "doc": "",
          "name": "from",
          "type_": "address"
        },
        {
          "doc": "",
          "name": "to",
          "type_": "address"
        }
      ],
      "outputs": [
        "i128"
      ]
    }
  },
  {
    "udt_union_v0": {
      "doc": "",
      "lib": "",
      "name": "DataKey",
      "cases": [
        {
          "void_v0": {
            "doc": "",
            "name": "Initialized"
          }
        },
        {
          "void_v0": {
            "doc": "",
            "name": "Registry"
          }
        },
        {
          "void_v0": {
            "doc": "",
            "name": "Asset"
          }
        },
        {
          "void_v0": {
            "doc": "",
            "name": "PairedAsset"
          }
        },
        {
          "void_v0": {
            "doc": "",
            "name": "Router"
          }
        },
        {
          "void_v0": {
            "doc": "",
            "name": "PoolIndex"
          }
        },
        {
          "void_v0": {
            "doc": "",
            "name": "SortedTokens"
          }
        },
        {
          "void_v0": {
            "doc": "AQUA emission token. On v1 mainnet harvest is a no-op (thin pools, no\\nverified pool_index for AQUA/asset swap). v1.1 will claim + compound.",
            "name": "RewardToken"
          }
        },
        {
          "void_v0": {
            "doc": "",
            "name": "TotalShares"
          }
        },
        {
          "tuple_v0": {
            "doc": "",
            "name": "Shares",
            "type_": [
              "address"
            ]
          }
        }
      ]
    }
  },
  {
    "function_v0": {
      "doc": "",
      "name": "initialize",
      "inputs": [
        {
          "doc": "",
          "name": "registry",
          "type_": "address"
        },
        {
          "doc": "",
          "name": "asset",
          "type_": "address"
        },
        {
          "doc": "",
          "name": "paired_asset",
          "type_": "address"
        },
        {
          "doc": "",
          "name": "router",
          "type_": "address"
        },
        {
          "doc": "",
          "name": "pool_index",
          "type_": {
            "bytes_n": {
              "n": 32
            }
          }
        },
        {
          "doc": "",
          "name": "reward_token",
          "type_": "address"
        }
      ],
      "outputs": []
    }
  },
  {
    "function_v0": {
      "doc": "",
      "name": "share_price",
      "inputs": [],
      "outputs": [
        "i128"
      ]
    }
  },
  {
    "function_v0": {
      "doc": "",
      "name": "total_shares",
      "inputs": [],
      "outputs": [
        "i128"
      ]
    }
  },
  {
    "function_v0": {
      "doc": "",
      "name": "share_balance",
      "inputs": [
        {
          "doc": "",
          "name": "from",
          "type_": "address"
        }
      ],
      "outputs": [
        "i128"
      ]
    }
  }
]