[
  {
    "udt_union_v0": {
      "doc": "",
      "lib": "",
      "name": "DataKey",
      "cases": [
        {
          "tuple_v0": {
            "doc": "",
            "name": "Balance",
            "type_": [
              "address"
            ]
          }
        }
      ]
    }
  },
  {
    "udt_error_enum_v0": {
      "doc": "",
      "lib": "",
      "name": "Error",
      "cases": [
        {
          "doc": "",
          "name": "AlreadyInitialized",
          "value": 1
        },
        {
          "doc": "",
          "name": "NotInitialized",
          "value": 2
        },
        {
          "doc": "",
          "name": "NegativeAmount",
          "value": 3
        },
        {
          "doc": "",
          "name": "ZeroOrNegativeAmount",
          "value": 4
        },
        {
          "doc": "",
          "name": "NoBalance",
          "value": 5
        }
      ]
    }
  },
  {
    "event_v0": {
      "doc": "",
      "lib": "",
      "name": "BalanceSetEvent",
      "prefix_topics": [
        "balance_set_event"
      ],
      "params": [
        {
          "doc": "",
          "name": "user",
          "type_": "address",
          "location": "data"
        },
        {
          "doc": "",
          "name": "old_balance",
          "type_": "i128",
          "location": "data"
        },
        {
          "doc": "",
          "name": "new_balance",
          "type_": "i128",
          "location": "data"
        }
      ],
      "data_format": "map"
    }
  },
  {
    "event_v0": {
      "doc": "",
      "lib": "",
      "name": "BalanceAddedEvent",
      "prefix_topics": [
        "balance_added_event"
      ],
      "params": [
        {
          "doc": "",
          "name": "user",
          "type_": "address",
          "location": "data"
        },
        {
          "doc": "",
          "name": "old_balance",
          "type_": "i128",
          "location": "data"
        },
        {
          "doc": "",
          "name": "new_balance",
          "type_": "i128",
          "location": "data"
        }
      ],
      "data_format": "map"
    }
  },
  {
    "event_v0": {
      "doc": "",
      "lib": "",
      "name": "WithdrawEvent",
      "prefix_topics": [
        "withdraw_event"
      ],
      "params": [
        {
          "doc": "",
          "name": "user",
          "type_": "address",
          "location": "data"
        },
        {
          "doc": "",
          "name": "amount",
          "type_": "i128",
          "location": "data"
        }
      ],
      "data_format": "map"
    }
  },
  {
    "event_v0": {
      "doc": "",
      "lib": "",
      "name": "AdminTransferEvent",
      "prefix_topics": [
        "admin_transfer_event"
      ],
      "params": [
        {
          "doc": "",
          "name": "old_admin",
          "type_": "address",
          "location": "data"
        },
        {
          "doc": "",
          "name": "new_admin",
          "type_": "address",
          "location": "data"
        }
      ],
      "data_format": "map"
    }
  },
  {
    "function_v0": {
      "doc": "Initialize the contract with USDC token address\\nThe caller becomes the admin (must sign the transaction)\\nCan only be called once",
      "name": "init",
      "inputs": [
        {
          "doc": "",
          "name": "admin",
          "type_": "address"
        },
        {
          "doc": "",
          "name": "usdc_address",
          "type_": "address"
        }
      ],
      "outputs": [
        {
          "result": {
            "ok_type": {
              "tuple": {
                "value_types": []
              }
            },
            "error_type": "error"
          }
        }
      ]
    }
  },
  {
    "function_v0": {
      "doc": "Set the balance for a user (Admin only)\\nThis will overwrite the existing balance",
      "name": "set_balance",
      "inputs": [
        {
          "doc": "",
          "name": "user",
          "type_": "address"
        },
        {
          "doc": "",
          "name": "amount",
          "type_": "i128"
        }
      ],
      "outputs": [
        {
          "result": {
            "ok_type": {
              "tuple": {
                "value_types": []
              }
            },
            "error_type": "error"
          }
        }
      ]
    }
  },
  {
    "function_v0": {
      "doc": "Add to the balance for a user (Admin only)\\nThis will add to the existing balance",
      "name": "add_balance",
      "inputs": [
        {
          "doc": "",
          "name": "user",
          "type_": "address"
        },
        {
          "doc": "",
          "name": "amount",
          "type_": "i128"
        }
      ],
      "outputs": [
        {
          "result": {
            "ok_type": {
              "tuple": {
                "value_types": []
              }
            },
            "error_type": "error"
          }
        }
      ]
    }
  },
  {
    "function_v0": {
      "doc": "Batch set balances for multiple users (Admin only)\\nThis will overwrite existing balances for all users in the list",
      "name": "batch_set_balance",
      "inputs": [
        {
          "doc": "",
          "name": "users",
          "type_": {
            "vec": {
              "element_type": "address"
            }
          }
        },
        {
          "doc": "",
          "name": "amounts",
          "type_": {
            "vec": {
              "element_type": "i128"
            }
          }
        }
      ],
      "outputs": [
        {
          "result": {
            "ok_type": {
              "tuple": {
                "value_types": []
              }
            },
            "error_type": "error"
          }
        }
      ]
    }
  },
  {
    "function_v0": {
      "doc": "Batch add to balances for multiple users (Admin only)\\nThis will add to existing balances for all users in the list",
      "name": "batch_add_balance",
      "inputs": [
        {
          "doc": "",
          "name": "users",
          "type_": {
            "vec": {
              "element_type": "address"
            }
          }
        },
        {
          "doc": "",
          "name": "amounts",
          "type_": {
            "vec": {
              "element_type": "i128"
            }
          }
        }
      ],
      "outputs": [
        {
          "result": {
            "ok_type": {
              "tuple": {
                "value_types": []
              }
            },
            "error_type": "error"
          }
        }
      ]
    }
  },
  {
    "function_v0": {
      "doc": "Withdraw all available USDC balance to the caller\\nRequires authorization from the user",
      "name": "withdraw",
      "inputs": [
        {
          "doc": "",
          "name": "user",
          "type_": "address"
        }
      ],
      "outputs": [
        {
          "result": {
            "ok_type": {
              "tuple": {
                "value_types": []
              }
            },
            "error_type": "error"
          }
        }
      ]
    }
  },
  {
    "function_v0": {
      "doc": "Get the balance for a user",
      "name": "get_balance",
      "inputs": [
        {
          "doc": "",
          "name": "user",
          "type_": "address"
        }
      ],
      "outputs": [
        "i128"
      ]
    }
  },
  {
    "function_v0": {
      "doc": "Get the admin address",
      "name": "get_admin",
      "inputs": [],
      "outputs": [
        "address"
      ]
    }
  },
  {
    "function_v0": {
      "doc": "Get the USDC token address",
      "name": "get_usdc",
      "inputs": [],
      "outputs": [
        "address"
      ]
    }
  },
  {
    "function_v0": {
      "doc": "Transfer admin to a new address (Admin only)",
      "name": "transfer_admin",
      "inputs": [
        {
          "doc": "",
          "name": "new_admin",
          "type_": "address"
        }
      ],
      "outputs": []
    }
  }
]