[
  {
    "udt_struct_v0": {
      "doc": "Public input type for Config - uses Vec for simplicity",
      "lib": "",
      "name": "ConfigInput",
      "fields": [
        {
          "doc": "",
          "name": "owners",
          "type_": {
            "vec": {
              "element_type": "address"
            }
          }
        },
        {
          "doc": "",
          "name": "threshold",
          "type_": "u32"
        }
      ]
    }
  },
  {
    "udt_struct_v0": {
      "doc": "",
      "lib": "",
      "name": "Config",
      "fields": [
        {
          "doc": "",
          "name": "owners",
          "type_": {
            "map": {
              "key_type": "address",
              "value_type": {
                "tuple": {
                  "value_types": []
                }
              }
            }
          }
        },
        {
          "doc": "",
          "name": "threshold",
          "type_": "u32"
        }
      ]
    }
  },
  {
    "udt_struct_v0": {
      "doc": "",
      "lib": "",
      "name": "Proposal",
      "fields": [
        {
          "doc": "",
          "name": "caller",
          "type_": "address"
        },
        {
          "doc": "",
          "name": "id",
          "type_": "u64"
        },
        {
          "doc": "",
          "name": "proposal_type",
          "type_": {
            "udt": {
              "name": "ProposalType"
            }
          }
        },
        {
          "doc": "",
          "name": "status",
          "type_": {
            "udt": {
              "name": "ProposalStatus"
            }
          }
        },
        {
          "doc": "",
          "name": "votes",
          "type_": {
            "vec": {
              "element_type": {
                "udt": {
                  "name": "Vote"
                }
              }
            }
          }
        }
      ]
    }
  },
  {
    "udt_enum_v0": {
      "doc": "",
      "lib": "",
      "name": "ProposalStatus",
      "cases": [
        {
          "doc": "",
          "name": "Pending",
          "value": 0
        },
        {
          "doc": "",
          "name": "Approved",
          "value": 1
        },
        {
          "doc": "",
          "name": "Rejected",
          "value": 2
        },
        {
          "doc": "",
          "name": "Executed",
          "value": 3
        },
        {
          "doc": "",
          "name": "Revoked",
          "value": 4
        }
      ]
    }
  },
  {
    "udt_struct_v0": {
      "doc": "",
      "lib": "",
      "name": "Vote",
      "fields": [
        {
          "doc": "",
          "name": "vote",
          "type_": {
            "udt": {
              "name": "VoteType"
            }
          }
        },
        {
          "doc": "",
          "name": "voter",
          "type_": "address"
        }
      ]
    }
  },
  {
    "udt_enum_v0": {
      "doc": "",
      "lib": "",
      "name": "VoteType",
      "cases": [
        {
          "doc": "",
          "name": "Abstain",
          "value": 0
        },
        {
          "doc": "",
          "name": "Yes",
          "value": 1
        },
        {
          "doc": "",
          "name": "No",
          "value": 2
        }
      ]
    }
  },
  {
    "udt_union_v0": {
      "doc": "Public input type for Config proposals - uses Vec for simplicity",
      "lib": "",
      "name": "ProposalInput",
      "cases": [
        {
          "tuple_v0": {
            "doc": "",
            "name": "Config",
            "type_": [
              {
                "udt": {
                  "name": "ConfigInput"
                }
              }
            ]
          }
        },
        {
          "tuple_v0": {
            "doc": "",
            "name": "UserRules",
            "type_": [
              {
                "udt": {
                  "name": "UserRules"
                }
              }
            ]
          }
        },
        {
          "tuple_v0": {
            "doc": "",
            "name": "RevokeUserRules",
            "type_": [
              "address"
            ]
          }
        },
        {
          "tuple_v0": {
            "doc": "",
            "name": "Invoke",
            "type_": [
              {
                "udt": {
                  "name": "Call"
                }
              }
            ]
          }
        },
        {
          "tuple_v0": {
            "doc": "",
            "name": "Upgrade",
            "type_": [
              {
                "bytes_n": {
                  "n": 32
                }
              }
            ]
          }
        }
      ]
    }
  },
  {
    "udt_union_v0": {
      "doc": "",
      "lib": "",
      "name": "ProposalType",
      "cases": [
        {
          "tuple_v0": {
            "doc": "",
            "name": "Config",
            "type_": [
              {
                "udt": {
                  "name": "Config"
                }
              }
            ]
          }
        },
        {
          "tuple_v0": {
            "doc": "",
            "name": "UserRules",
            "type_": [
              {
                "udt": {
                  "name": "UserRules"
                }
              }
            ]
          }
        },
        {
          "tuple_v0": {
            "doc": "",
            "name": "RevokeUserRules",
            "type_": [
              "address"
            ]
          }
        },
        {
          "tuple_v0": {
            "doc": "",
            "name": "Invoke",
            "type_": [
              {
                "udt": {
                  "name": "Call"
                }
              }
            ]
          }
        },
        {
          "tuple_v0": {
            "doc": "",
            "name": "Upgrade",
            "type_": [
              {
                "bytes_n": {
                  "n": 32
                }
              }
            ]
          }
        }
      ]
    }
  },
  {
    "udt_struct_v0": {
      "doc": "",
      "lib": "",
      "name": "UserRules",
      "fields": [
        {
          "doc": "",
          "name": "rules",
          "type_": {
            "vec": {
              "element_type": {
                "udt": {
                  "name": "RuleSet"
                }
              }
            }
          }
        },
        {
          "doc": "",
          "name": "user",
          "type_": "address"
        }
      ]
    }
  },
  {
    "udt_union_v0": {
      "doc": "",
      "lib": "",
      "name": "RuleSet",
      "cases": [
        {
          "tuple_v0": {
            "doc": "",
            "name": "All",
            "type_": [
              {
                "vec": {
                  "element_type": {
                    "udt": {
                      "name": "Rule"
                    }
                  }
                }
              }
            ]
          }
        }
      ]
    }
  },
  {
    "udt_struct_v0": {
      "doc": "",
      "lib": "",
      "name": "Call",
      "fields": [
        {
          "doc": "",
          "name": "address",
          "type_": "address"
        },
        {
          "doc": "",
          "name": "args",
          "type_": {
            "vec": {
              "element_type": "val"
            }
          }
        },
        {
          "doc": "",
          "name": "fn_name",
          "type_": "symbol"
        }
      ]
    }
  },
  {
    "udt_union_v0": {
      "doc": "",
      "lib": "",
      "name": "Comparator",
      "cases": [
        {
          "void_v0": {
            "doc": "",
            "name": "Eq"
          }
        },
        {
          "void_v0": {
            "doc": "",
            "name": "Gt"
          }
        },
        {
          "void_v0": {
            "doc": "",
            "name": "Gte"
          }
        },
        {
          "void_v0": {
            "doc": "",
            "name": "Lt"
          }
        },
        {
          "void_v0": {
            "doc": "",
            "name": "Lte"
          }
        }
      ]
    }
  },
  {
    "udt_union_v0": {
      "doc": "",
      "lib": "",
      "name": "ValueType",
      "cases": [
        {
          "tuple_v0": {
            "doc": "",
            "name": "U32",
            "type_": [
              "u32"
            ]
          }
        },
        {
          "tuple_v0": {
            "doc": "",
            "name": "I32",
            "type_": [
              "i32"
            ]
          }
        },
        {
          "tuple_v0": {
            "doc": "",
            "name": "U64",
            "type_": [
              "u64"
            ]
          }
        },
        {
          "tuple_v0": {
            "doc": "",
            "name": "I64",
            "type_": [
              "i64"
            ]
          }
        },
        {
          "tuple_v0": {
            "doc": "",
            "name": "U128",
            "type_": [
              "u128"
            ]
          }
        },
        {
          "tuple_v0": {
            "doc": "",
            "name": "I128",
            "type_": [
              "i128"
            ]
          }
        },
        {
          "tuple_v0": {
            "doc": "",
            "name": "Bool",
            "type_": [
              "bool"
            ]
          }
        },
        {
          "tuple_v0": {
            "doc": "",
            "name": "Address",
            "type_": [
              "address"
            ]
          }
        },
        {
          "tuple_v0": {
            "doc": "",
            "name": "Symbol",
            "type_": [
              "symbol"
            ]
          }
        }
      ]
    }
  },
  {
    "udt_struct_v0": {
      "doc": "",
      "lib": "",
      "name": "Rule",
      "fields": [
        {
          "doc": "",
          "name": "comparator",
          "type_": {
            "udt": {
              "name": "Comparator"
            }
          }
        },
        {
          "doc": "",
          "name": "field",
          "type_": {
            "udt": {
              "name": "RuleField"
            }
          }
        },
        {
          "doc": "",
          "name": "value",
          "type_": {
            "udt": {
              "name": "ValueType"
            }
          }
        }
      ]
    }
  },
  {
    "udt_union_v0": {
      "doc": "",
      "lib": "",
      "name": "RuleField",
      "cases": [
        {
          "void_v0": {
            "doc": "",
            "name": "FnName"
          }
        },
        {
          "void_v0": {
            "doc": "",
            "name": "ContractAddress"
          }
        },
        {
          "tuple_v0": {
            "doc": "",
            "name": "Arg",
            "type_": [
              "u32"
            ]
          }
        }
      ]
    }
  },
  {
    "udt_error_enum_v0": {
      "doc": "",
      "lib": "",
      "name": "ContractError",
      "cases": [
        {
          "doc": "",
          "name": "NotInitialized",
          "value": 2
        },
        {
          "doc": "",
          "name": "InvalidOwners",
          "value": 5
        },
        {
          "doc": "",
          "name": "InvalidThreshold",
          "value": 6
        },
        {
          "doc": "",
          "name": "NotOwner",
          "value": 8
        },
        {
          "doc": "",
          "name": "ProposalNotFound",
          "value": 9
        },
        {
          "doc": "",
          "name": "VoterAlreadyVoted",
          "value": 10
        },
        {
          "doc": "",
          "name": "ProposalNotPending",
          "value": 11
        },
        {
          "doc": "",
          "name": "InvokeError",
          "value": 12
        },
        {
          "doc": "",
          "name": "NotUser",
          "value": 13
        },
        {
          "doc": "",
          "name": "NoConfigChanges",
          "value": 14
        },
        {
          "doc": "",
          "name": "NotCaller",
          "value": 15
        },
        {
          "doc": "",
          "name": "RuleNotAllowed",
          "value": 18
        },
        {
          "doc": "",
          "name": "InvokeNotAllowed",
          "value": 19
        },
        {
          "doc": "",
          "name": "EmptyUserRules",
          "value": 20
        },
        {
          "doc": "",
          "name": "NoRulesToRevoke",
          "value": 21
        },
        {
          "doc": "",
          "name": "InvalidUpgrade",
          "value": 22
        },
        {
          "doc": "",
          "name": "InvalidInvoke",
          "value": 23
        },
        {
          "doc": "",
          "name": "DuplicateRulesets",
          "value": 24
        }
      ]
    }
  },
  {
    "function_v0": {
      "doc": "",
      "name": "__constructor",
      "inputs": [
        {
          "doc": "",
          "name": "config",
          "type_": {
            "option": {
              "value_type": {
                "udt": {
                  "name": "ConfigInput"
                }
              }
            }
          }
        }
      ],
      "outputs": [
        {
          "result": {
            "ok_type": {
              "tuple": {
                "value_types": []
              }
            },
            "error_type": {
              "udt": {
                "name": "ContractError"
              }
            }
          }
        }
      ]
    }
  },
  {
    "function_v0": {
      "doc": "",
      "name": "version",
      "inputs": [],
      "outputs": [
        "u32"
      ]
    }
  },
  {
    "function_v0": {
      "doc": "",
      "name": "get_config",
      "inputs": [],
      "outputs": [
        {
          "result": {
            "ok_type": {
              "udt": {
                "name": "ConfigInput"
              }
            },
            "error_type": {
              "udt": {
                "name": "ContractError"
              }
            }
          }
        }
      ]
    }
  },
  {
    "function_v0": {
      "doc": "* Proposes a new proposal. The caller must be an owner, and the proposal\\n     * must be valid (and not an Invoke attempt).",
      "name": "propose",
      "inputs": [
        {
          "doc": "",
          "name": "owner",
          "type_": "address"
        },
        {
          "doc": "",
          "name": "proposal",
          "type_": {
            "udt": {
              "name": "ProposalInput"
            }
          }
        }
      ],
      "outputs": [
        {
          "result": {
            "ok_type": {
              "udt": {
                "name": "Proposal"
              }
            },
            "error_type": {
              "udt": {
                "name": "ContractError"
              }
            }
          }
        }
      ]
    }
  },
  {
    "function_v0": {
      "doc": "",
      "name": "invoke",
      "inputs": [
        {
          "doc": "",
          "name": "caller",
          "type_": "address"
        },
        {
          "doc": "",
          "name": "contract",
          "type_": "address"
        },
        {
          "doc": "",
          "name": "fn_name",
          "type_": "symbol"
        },
        {
          "doc": "",
          "name": "args",
          "type_": {
            "vec": {
              "element_type": "val"
            }
          }
        }
      ],
      "outputs": [
        {
          "result": {
            "ok_type": {
              "tuple": {
                "value_types": []
              }
            },
            "error_type": {
              "udt": {
                "name": "ContractError"
              }
            }
          }
        }
      ]
    }
  },
  {
    "function_v0": {
      "doc": "",
      "name": "revoke_proposal",
      "inputs": [
        {
          "doc": "",
          "name": "caller",
          "type_": "address"
        },
        {
          "doc": "",
          "name": "proposal_id",
          "type_": "u64"
        }
      ],
      "outputs": [
        {
          "result": {
            "ok_type": {
              "tuple": {
                "value_types": []
              }
            },
            "error_type": {
              "udt": {
                "name": "ContractError"
              }
            }
          }
        }
      ]
    }
  },
  {
    "function_v0": {
      "doc": "",
      "name": "vote",
      "inputs": [
        {
          "doc": "",
          "name": "owner",
          "type_": "address"
        },
        {
          "doc": "",
          "name": "proposal_id",
          "type_": "u64"
        },
        {
          "doc": "",
          "name": "vote",
          "type_": {
            "udt": {
              "name": "VoteType"
            }
          }
        }
      ],
      "outputs": [
        {
          "result": {
            "ok_type": {
              "udt": {
                "name": "Proposal"
              }
            },
            "error_type": {
              "udt": {
                "name": "ContractError"
              }
            }
          }
        }
      ]
    }
  }
]